model_finetune/__init__.py
model_finetune/_version.py
model_finetune/common_validators.py
model_finetune/core_processor.py
model_finetune/data_merger.py
model_finetune/data_processor.py
model_finetune/downloader.py
model_finetune/exceptions.py
model_finetune/extractor.py
model_finetune/geo_utils.py
model_finetune/main.py
model_finetune/unified_interface.py
model_finetune/utils.py
model_finetune/validators.py
model_finetune-1.1.0.dist-info/licenses/LICENSE
model_finetune-1.1.0.dist-info/METADATA
model_finetune-1.1.0.dist-info/WHEEL
model_finetune-1.1.0.dist-info/top_level.txt
model_finetune-1.1.0.dist-info/RECORD
