Metadata-Version: 2.4
Name: model-finetune
Version: 1.1.0
Summary: 智能模型微调和自动建模工具包 - 专业的光谱数据处理和机器学习建模解决方案
Author-email: "周元琦 (Yuan-Qi Zhou)" <zyq1034378361@gmail.com>
Maintainer-email: "周元琦 (Yuan-Qi Zhou)" <zyq1034378361@gmail.com>
License: MIT (Non-Commercial Use Only)
Project-URL: Homepage, https://github.com/1034378361/model-finetune
Project-URL: Documentation, https://github.com/1034378361/model-finetune/blob/main/README.md
Project-URL: Repository, https://github.com/1034378361/model-finetune.git
Project-URL: Issues, https://github.com/1034378361/model-finetune/issues
Project-URL: Changelog, https://github.com/1034378361/model-finetune/blob/main/CHANGELOG.md
Keywords: model-finetune,automl,machine-learning,fine-tuning,model-optimization,automated-modeling,ml-pipeline,spectral-analysis,data-fusion,geo-matching
Classifier: Development Status :: 5 - Production/Stable
Classifier: Intended Audience :: Science/Research
Classifier: Intended Audience :: Developers
Classifier: License :: OSI Approved :: MIT License
Classifier: Programming Language :: Python :: 3
Classifier: Programming Language :: Python :: 3.8
Classifier: Programming Language :: Python :: 3.9
Classifier: Programming Language :: Python :: 3.10
Classifier: Programming Language :: Python :: 3.11
Classifier: Programming Language :: Python :: 3.12
Classifier: Topic :: Scientific/Engineering :: Artificial Intelligence
Classifier: Topic :: Scientific/Engineering :: GIS
Classifier: Topic :: Scientific/Engineering :: Image Processing
Classifier: Topic :: Scientific/Engineering :: Physics
Classifier: Operating System :: OS Independent
Requires-Python: >=3.10
License-File: LICENSE
Requires-Dist: numpy>=2.2.0
Requires-Dist: pandas>=2.2.0
Requires-Dist: scikit-learn>=1.6.0
Requires-Dist: scipy>=1.15.0
Requires-Dist: requests>=2.32.0
Requires-Dist: chardet>=5.2.0
Requires-Dist: cryptography>=44.0.0
Requires-Dist: autowaterqualitymodeler>=4.0.5
Requires-Dist: python-dotenv>=1.0.0
Requires-Dist: psutil>=6.1.0
Requires-Dist: tqdm>=4.66.0
Provides-Extra: dev
Requires-Dist: pytest>=8.0.0; extra == "dev"
Requires-Dist: pytest-cov>=6.0.0; extra == "dev"
Requires-Dist: pytest-xdist>=3.6.0; extra == "dev"
Requires-Dist: black>=24.0.0; extra == "dev"
Requires-Dist: isort>=5.13.0; extra == "dev"
Requires-Dist: flake8>=7.0.0; extra == "dev"
Requires-Dist: mypy>=1.8.0; extra == "dev"
Requires-Dist: pre-commit>=4.0.0; extra == "dev"
Provides-Extra: docs
Requires-Dist: mkdocs>=1.6.0; extra == "docs"
Requires-Dist: mkdocs-material>=9.5.0; extra == "docs"
Requires-Dist: mkdocstrings[python]>=0.26.0; extra == "docs"
Provides-Extra: viz
Requires-Dist: matplotlib>=3.8.0; extra == "viz"
Requires-Dist: seaborn>=0.13.0; extra == "viz"
Requires-Dist: plotly>=5.17.0; extra == "viz"
Requires-Dist: folium>=0.15.0; extra == "viz"
Provides-Extra: all
Requires-Dist: model-finetune[dev,docs,viz]; extra == "all"
Dynamic: license-file
